lirix/DiceAgent.py
lirix/Wiki_Agent.py
lirix/__init__.py
lirix/agent_class.py
lirix/load_api_key.py
lirix/searchAgent.py
lirix_ai-0.0.1.dist-info/METADATA
lirix_ai-0.0.1.dist-info/WHEEL
lirix_ai-0.0.1.dist-info/top_level.txt
lirix_ai-0.0.1.dist-info/RECORD
