Metadata-Version: 2.2
Name: lirix-ai
Version: 0.0.1
Summary: Add your description here
Author: Abhiram, Tanishq
Requires-Python: >=3.13
Requires-Dist: aiohttp>=3.11.13
Requires-Dist: asyncio>=3.4.3
Requires-Dist: nest-asyncio>=1.6.0
Requires-Dist: pydantic>=2.10.6
Requires-Dist: pydantic-ai>=0.0.39
Requires-Dist: pydantic-settings>=2.8.1
Requires-Dist: setuptools>=76.0.0
Requires-Dist: tavily-python>=0.5.1
Requires-Dist: twine>=6.1.0
Dynamic: author
